repoforge/__init__.py
repoforge/repoforge.py
repoforge-0.1.7.dist-info/LICENSE
repoforge-0.1.7.dist-info/METADATA
repoforge-0.1.7.dist-info/WHEEL
repoforge-0.1.7.dist-info/entry_points.txt
repoforge-0.1.7.dist-info/top_level.txt
repoforge-0.1.7.dist-info/RECORD
