Metadata-Version: 2.2
Name: repoforge
Version: 0.1.7
Summary: Generate a formatted LLM prompt from a repository directory.
Home-page: https://github.com/ahearn15/repoforge/
Author: Adam Hearn
Author-email: ahearn15@gmail.com
Classifier: Programming Language :: Python :: 3
Classifier: License :: OSI Approved :: MIT License
Classifier: Operating System :: OS Independent
Requires-Python: >=3.6
License-File: LICENSE
Dynamic: author
Dynamic: author-email
Dynamic: classifier
Dynamic: description
Dynamic: description-content-type
Dynamic: home-page
Dynamic: requires-python
Dynamic: summary
